dotref/__init__.py
dotref-1.2.4.dist-info/LICENSE
dotref-1.2.4.dist-info/METADATA
dotref-1.2.4.dist-info/WHEEL
dotref-1.2.4.dist-info/entry_points.txt
dotref-1.2.4.dist-info/top_level.txt
dotref-1.2.4.dist-info/RECORD
