Metadata-Version: 2.1
Name: dotref
Version: 1.2.4
Summary: Simple tool to manage dotfiles
Home-page: https://github.com/ovk/dotref
Download-URL: https://github.com/ovk/dotref/archive/v1.2.4.tar.gz
Author: ovk
Author-email: mail@okosh.xyz
License: MIT
Project-URL: Bug Tracker, https://github.com/ovk/dotref/issues
Keywords: dotfiles
Classifier: Programming Language :: Python :: 3.6
Classifier: Programming Language :: Python :: 3.7
Classifier: Programming Language :: Python :: 3.8
Classifier: Programming Language :: Python :: 3.9
Classifier: Programming Language :: Python :: 3.10
Classifier: License :: OSI Approved :: MIT License
Classifier: Operating System :: OS Independent
Requires-Python: >=3.6
License-File: LICENSE
Provides-Extra: test
Requires-Dist: coverage ; extra == 'test'
